topophonon/__init__.py
topophonon/masses.py
topophonon/model.py
topophonon/runExample.py
topophonon/structure.py
topophonon/topology.py
topophonon/units.py
topoPhonon-1.0.3.dist-info/LICENSE
topoPhonon-1.0.3.dist-info/METADATA
topoPhonon-1.0.3.dist-info/WHEEL
topoPhonon-1.0.3.dist-info/top_level.txt
topoPhonon-1.0.3.dist-info/RECORD
