Metadata-Version: 2.1
Name: topoPhonon
Version: 1.0.3
Summary: topoPhonon package is a python package that allows users tophononic calculate topological properties, by building phonon tight-bindingmodel.
Home-page: https://github.com/cnncnnzh/topoPhonon
Author: He Zhu
Author-email: zhu00336@umn.edu
Classifier: Programming Language :: Python :: 3
Classifier: License :: OSI Approved :: GNU General Public License v3 (GPLv3)
Classifier: Operating System :: OS Independent
Requires-Python: >=3.8
License-File: LICENSE
Requires-Dist: matplotlib (>=3.5.2)
Requires-Dist: numpy (>=1.23.1)
Requires-Dist: tqdm (>=4.64.1)
Requires-Dist: scipy (>=1.6.2)
